wasmpy_build/__init__.py
wasmpy_build/cli.py
wasmpy_build/compiler.py
wasmpy_build/core.py
wasmpy_build/include/cp310/LICENSE
wasmpy_build/include/cp310/Python.h
wasmpy_build/include/cp310/README.rst
wasmpy_build/include/cp310/abstract.h
wasmpy_build/include/cp310/bltinmodule.h
wasmpy_build/include/cp310/boolobject.h
wasmpy_build/include/cp310/bytearrayobject.h
wasmpy_build/include/cp310/bytesobject.h
wasmpy_build/include/cp310/cellobject.h
wasmpy_build/include/cp310/ceval.h
wasmpy_build/include/cp310/classobject.h
wasmpy_build/include/cp310/code.h
wasmpy_build/include/cp310/codecs.h
wasmpy_build/include/cp310/compile.h
wasmpy_build/include/cp310/complexobject.h
wasmpy_build/include/cp310/context.h
wasmpy_build/include/cp310/datetime.h
wasmpy_build/include/cp310/descrobject.h
wasmpy_build/include/cp310/dictobject.h
wasmpy_build/include/cp310/dynamic_annotations.h
wasmpy_build/include/cp310/enumobject.h
wasmpy_build/include/cp310/errcode.h
wasmpy_build/include/cp310/eval.h
wasmpy_build/include/cp310/exports.h
wasmpy_build/include/cp310/fileobject.h
wasmpy_build/include/cp310/fileutils.h
wasmpy_build/include/cp310/floatobject.h
wasmpy_build/include/cp310/frameobject.h
wasmpy_build/include/cp310/funcobject.h
wasmpy_build/include/cp310/genericaliasobject.h
wasmpy_build/include/cp310/genobject.h
wasmpy_build/include/cp310/import.h
wasmpy_build/include/cp310/interpreteridobject.h
wasmpy_build/include/cp310/intrcheck.h
wasmpy_build/include/cp310/iterobject.h
wasmpy_build/include/cp310/listobject.h
wasmpy_build/include/cp310/longintrepr.h
wasmpy_build/include/cp310/longobject.h
wasmpy_build/include/cp310/marshal.h
wasmpy_build/include/cp310/memoryobject.h
wasmpy_build/include/cp310/methodobject.h
wasmpy_build/include/cp310/modsupport.h
wasmpy_build/include/cp310/moduleobject.h
wasmpy_build/include/cp310/namespaceobject.h
wasmpy_build/include/cp310/object.h
wasmpy_build/include/cp310/objimpl.h
wasmpy_build/include/cp310/opcode.h
wasmpy_build/include/cp310/osdefs.h
wasmpy_build-1.0.0.dist-info/LICENSE
wasmpy_build-1.0.0.dist-info/METADATA
wasmpy_build-1.0.0.dist-info/WHEEL
wasmpy_build-1.0.0.dist-info/entry_points.txt
wasmpy_build-1.0.0.dist-info/top_level.txt
wasmpy_build-1.0.0.dist-info/RECORD
