Metadata-Version: 2.1
Name: wasmpy-build
Version: 1.0.0
Summary: WebAssembly build tool for CPython C/C++ extensions
Author-email: Olivia Ryan <olivia.r.dev@gmail.com>
License: MIT License
Project-URL: Issues, https://github.com/olivi-r/wasmpy-build/issues
Project-URL: Repository, https://github.com/olivi-r/wasmpy-build
Classifier: Programming Language :: C
Classifier: Programming Language :: C++
Classifier: Programming Language :: Python :: 3
Classifier: Programming Language :: Python :: 3.6
Classifier: Programming Language :: Python :: 3.7
Classifier: Programming Language :: Python :: 3.8
Classifier: Programming Language :: Python :: 3.9
Classifier: Programming Language :: Python :: 3.10
Classifier: Programming Language :: Python :: 3.11
Classifier: Programming Language :: Python :: 3.12
Classifier: Programming Language :: Python :: Implementation :: CPython
Classifier: Environment :: WebAssembly
Classifier: Environment :: WebAssembly :: WASI
Classifier: License :: OSI Approved :: MIT License
Requires-Python: >=3.6
License-File: LICENSE
Requires-Dist: appdirs
Requires-Dist: requests
Requires-Dist: tqdm
